{
    "widgetName": "Rating1",
    "onRateChanged": "{{showAlert('Thank you!','info')}}",
    "displayName": "Rating",
    "iconSVG": "/static/media/icon.914eb943.svg",
    "topRow": 70,
    "bottomRow": 77,
    "parentRowSpace": 10,
    "type": "RATE_WIDGET",
    "maxCount": 5,
    "hideCard": false,
    "animateLoading": true,
    "parentColumnSpace": 13.310546875,
    "dynamicTriggerPathList": [{"key": "onRateChanged"}],
    "leftColumn": 39,
    "dynamicBindingPathList": [{"key": "activeColor"}],
    "isDisabled": false,
    "key": "p1mthoi158",
    "isRequired": false,
    "isDeprecated": false,
    "rightColumn": 63,
    "inactiveColor": "#D6D6D6",
    "dynamicHeight": "FIXED",
    "widgetId": "tg4b5ph78q",
    "isVisible": true,
    "parentId": "qwh5rks3ge",
    "renderMode": "CANVAS",
    "isLoading": false,
    "defaultRate": 3,
    "activeColor": "{{appsmith.theme.colors.primaryColor}}",
    "size": "MEDIUM",
    "maxDynamicHeight": 9000,
    "isAllowHalf": true,
    "minDynamicHeight": 4,
    "tooltips": [
        "Terrible",
        "Bad",
        "Neutral",
        "Good",
        "Great"
    ]
}